sql_xml_table/__init__.py
sql_xml_table-0.1.1.dist-info/DESCRIPTION.rst
sql_xml_table-0.1.1.dist-info/METADATA
sql_xml_table-0.1.1.dist-info/RECORD
sql_xml_table-0.1.1.dist-info/WHEEL
sql_xml_table-0.1.1.dist-info/metadata.json
sql_xml_table-0.1.1.dist-info/top_level.txt
