Metadata-Version: 2.0
Name: sql-xml-table
Version: 0.1.1
Summary: Small Python2/3 module to easily work with tables and import/export them to/from SQL databases and XML files
Home-page: https://github.com/WolfangT/sql_xml_table
Author: Wolfang Torres
Author-email: wolfang.torres@gmail.com
License: GNU
Keywords: SQL XML Table MySQL SQLite3
Platform: UNKNOWN
Requires-Python: >=2.6, <4
Requires-Dist: pymysql
Requires-Dist: python-sql
